CHANGES.rst
MANIFEST.in
README.rst
setup.py
src/djangorecipe/__init__.py
src/djangorecipe/binscripts.py
src/djangorecipe/boilerplate.py
src/djangorecipe/recipe.py
src/djangorecipe.egg-info/PKG-INFO
src/djangorecipe.egg-info/SOURCES.txt
src/djangorecipe.egg-info/dependency_links.txt
src/djangorecipe.egg-info/entry_points.txt
src/djangorecipe.egg-info/not-zip-safe
src/djangorecipe.egg-info/requires.txt
src/djangorecipe.egg-info/top_level.txt
src/djangorecipe/tests/__init__.py
src/djangorecipe/tests/test_scripts.py
src/djangorecipe/tests/tests.py